qfieldcloud_sdk/__init__.py
qfieldcloud_sdk/__main__.py
qfieldcloud_sdk/cli.py
qfieldcloud_sdk/interfaces.py
qfieldcloud_sdk/sdk.py
qfieldcloud_sdk/utils.py
qfieldcloud_sdk-0.12.0.dist-info/licenses/LICENCE
qfieldcloud_sdk-0.12.0.dist-info/METADATA
qfieldcloud_sdk-0.12.0.dist-info/WHEEL
qfieldcloud_sdk-0.12.0.dist-info/entry_points.txt
qfieldcloud_sdk-0.12.0.dist-info/top_level.txt
qfieldcloud_sdk-0.12.0.dist-info/RECORD
