Metadata-Version: 2.4
Name: qfieldcloud-sdk
Version: 0.12.0
Summary: The official QFieldCloud SDK and CLI.
Author-email: Ivan Ivanov <ivan@opengis.ch>
Project-URL: homepage, https://github.com/opengisch/qfieldcloud-sdk-python
Project-URL: documentation, https://github.com/opengisch/qfieldcloud-sdk-python
Project-URL: repository, https://github.com/opengisch/qfieldcloud-sdk-python
Project-URL: tracker, https://github.com/opengisch/qfieldcloud-sdk-python/issues
Keywords: QFieldCloud,QField,QGIS,CI,SDK,CLI
Classifier: Development Status :: 5 - Production/Stable
Classifier: Intended Audience :: System Administrators
Classifier: Intended Audience :: Developers
Classifier: Intended Audience :: Information Technology
Classifier: Operating System :: OS Independent
Classifier: Programming Language :: Python :: 3
Classifier: Programming Language :: Python :: 3.8
Classifier: Programming Language :: Python :: 3.9
Classifier: Programming Language :: Python :: 3.10
Classifier: Programming Language :: Python :: 3.11
Classifier: Programming Language :: Python :: 3.12
Classifier: Programming Language :: Python :: Implementation :: CPython
Classifier: Topic :: Scientific/Engineering :: GIS
Requires-Python: >=3.8
License-File: LICENCE
Requires-Dist: certifi>=2023.7.22
Requires-Dist: charset-normalizer>=3.2.0
Requires-Dist: click>=8.1.5
Requires-Dist: idna>=3.4
Requires-Dist: requests>=2.31.0
Requires-Dist: requests-toolbelt>=1.0.0
Requires-Dist: tqdm>=4.65.0
Requires-Dist: urllib3>=2.0.7
Requires-Dist: pathvalidate>=3.2.1
Provides-Extra: docs
Requires-Dist: mkdocstrings[python]~=0.25; extra == "docs"
Requires-Dist: mkdocs-click~=0.8.1; extra == "docs"
Requires-Dist: mkdocs-material~=9.5.17; extra == "docs"
Requires-Dist: fancyboxmd~=1.1; extra == "docs"
Dynamic: license-file
